README.md
setup.py
pytooltest/__init__.py
pytooltest/printtool.py
pytooltest.egg-info/PKG-INFO
pytooltest.egg-info/SOURCES.txt
pytooltest.egg-info/dependency_links.txt
pytooltest.egg-info/top_level.txt