Metadata-Version: 1.0
Name: pytooltest
Version: 0.1.0
Summary: pytooltest
Home-page: https://github.com/yvan233/pipproject
Author: yvan
Author-email: 2624507753@qq.com
License: MIT Licence
Keywords: pip,pytooltest
Platform: any
